[
  {
    "name": "Go backend service",
    "description": "Mobile app backend service develop with Go Gin framework and redis ",
    "github": "https://github.com/turgayh/go-backend.git"
  },
  {
    "name": "Game Leaderboard System Design",
    "description": "To create game leaderboard system and publishing to digitalocean",
    "github": "https://github.com/turgayh/game-leaderboard-system-design"
  },
  {
    "name": "Interactive-Migration-Map",
    "description": "Monitoring Refugee Crisis in the Aegean Sea",
    "github": "https://github.com/turgayh/Interactive-Migration-Map"
  },
  {
    "name": "Data Analysis in Fundamental Sciences",
    "description": "Using fundemantel of ML algorithm and implement on specific data",
    "github": "https://github.com/turgayh/MATH388E"
  },
  {
    "name": "Stock API",
    "description": "Commercial website stock tracking ",
    "github": "https://github.com/turgayh/Stock.WebApi"
  },
  {
    "name": "CollectSend",
    "description": "Android app develop with React-Native and Firebase",
    "github": "https://play.google.com/store/apps/details?id=com.collectsend"
  }
]
